wikidspark/__init__.py
wikidspark/data_structures.py
wikidspark/examples/__init__.py
wikidspark/examples/crs.py
wikidspark/examples/harry_potter_books.py
wikidspark/examples/hundred_books.py
wikidspark/examples/uk_railway_stations.py
wikidspark/exceptions.py
wikidspark/item.py
wikidspark/query.py
wikidspark/remote.py
wikidspark/sparql.py
wikidspark/wikidata/__init__.py
wikidspark/wikidata/_update.py
wikidspark/wikidata/catalogue.py
wikidspark/wikidata/common.py
wikidspark/wikidata/meta.py
wikidspark/wikidata/properties.json
wikidspark-0.3.0.dist-info/LICENSE
wikidspark-0.3.0.dist-info/METADATA
wikidspark-0.3.0.dist-info/WHEEL
wikidspark-0.3.0.dist-info/RECORD
