Metadata-Version: 2.3
Name: wikidspark
Version: 0.3.0
Summary: Wikidspark is an API for querying the Wikidata item database, allowing uses to search either directly by name or ID, or construct SPARQL queries
License: GPL-v3
Keywords: wikidata,sparql
Author: Kristian Zarębski
Author-email: krizar312@gmail.com
Requires-Python: >=3.10,<4.0
Classifier: Development Status :: 5 - Production/Stable
Classifier: License :: OSI Approved :: GNU General Public License v3 (GPLv3)
Classifier: License :: Other/Proprietary License
Classifier: Programming Language :: Python :: 3
Classifier: Programming Language :: Python :: 3.10
Classifier: Programming Language :: Python :: 3.11
Classifier: Programming Language :: Python :: 3.12
Classifier: Programming Language :: Python :: 3.13
Classifier: Topic :: Database
Classifier: Topic :: Internet
Requires-Dist: click (>=8.1.8,<9.0.0)
Requires-Dist: html-to-json (>=2.0.0,<3.0.0)
Requires-Dist: pandas (>=2.2.3,<3.0.0)
Requires-Dist: tqdm (>=4.67.1,<5.0.0)
Requires-Dist: urllib3 (>=2.3.0,<3.0.0)
Requires-Dist: wikipedia (>=1.4.0,<2.0.0)
Project-URL: Repository, https://github.com/artemis-beta/wikidspark
